usempl_plots/__init__.py
usempl_plots/get_payems.py
usempl_plots/tseries_payems.py
usempl_plots/usempl_industry.py
usempl_plots/usempl_npp.py
usempl_plots/usempl_streaks.py
usempl_plots/data/recession_data.csv
usempl_plots/data/usempl_2024-12-01.csv
usempl_plots/data/usempl_annual_1919-1938.csv
usempl_plots/data/usempl_pk_2024-12-01.csv
usempl_plots-0.0.9.dist-info/LICENSE
usempl_plots-0.0.9.dist-info/METADATA
usempl_plots-0.0.9.dist-info/WHEEL
usempl_plots-0.0.9.dist-info/top_level.txt
usempl_plots-0.0.9.dist-info/RECORD
