Metadata-Version: 2.2
Name: usempl-plots
Version: 0.0.9
Summary: Package for creating plots of US employment and unemployment
Home-page: https://github.com/OpenSourceEcon/usempl-plots
Download-URL: https://github.com/OpenSourceEcon/usempl-plots
Author: Richard W. Evans
License: CC0 1.0 Universal (CC0 1.0) Public Domain Dedication
Project-URL: Issue Tracker, https://github.com/OpenSourceEcon/usempl-plots/issues
Keywords: Data analysis visualization tools US employment unemployment
Classifier: Development Status :: 2 - Pre-Alpha
Classifier: Intended Audience :: End Users/Desktop
Classifier: Intended Audience :: Developers
Classifier: License :: CC0 1.0 Universal (CC0 1.0) Public Domain Dedication
Classifier: Natural Language :: English
Classifier: Operating System :: OS Independent
Classifier: Programming Language :: Python
Classifier: Programming Language :: Python :: 3.12
Classifier: Programming Language :: Python :: 3.13
Classifier: Topic :: Scientific/Engineering :: Information Analysis
Classifier: Topic :: Software Development :: Libraries :: Python Modules
Requires-Python: >=3.12
License-File: LICENSE
Requires-Dist: numpy>=1.23.4
Requires-Dist: scipy>=1.9.3
Requires-Dist: pandas>=1.5.2
Requires-Dist: pandas-datareader>=0.10.0
Requires-Dist: bokeh>=3.0
Requires-Dist: matplotlib
Requires-Dist: pytest>=7.1.2
Requires-Dist: pytest-cov
Requires-Dist: coverage>=6.3.2
Requires-Dist: codecov>=2.1.11
Requires-Dist: black>=24.1.1
Requires-Dist: pip>=22.3.1
Requires-Dist: linecheck>=0.1.0
Dynamic: author
Dynamic: classifier
Dynamic: description
Dynamic: description-content-type
Dynamic: download-url
Dynamic: home-page
Dynamic: keywords
Dynamic: license
Dynamic: project-url
Dynamic: requires-dist
Dynamic: requires-python
Dynamic: summary
